flask_json_logger/__init__.py
flask_json_logger-0.1.0.dist-info/LICENSE
flask_json_logger-0.1.0.dist-info/METADATA
flask_json_logger-0.1.0.dist-info/WHEEL
flask_json_logger-0.1.0.dist-info/top_level.txt
flask_json_logger-0.1.0.dist-info/RECORD
